MANIFEST.in
setup.py
devproject/__init__.py
devproject/manage.py
devproject/settings.py
devproject/urls.py
devproject/devtest/__init__.py
devproject/devtest/forms.py
devproject/devtest/models.py
devproject/devtest/views.py
devproject/templates/base.html
devproject/templates/homepage.html
devproject/templates/login.html
devproject/templates/logout.html
devproject/templates/signup.html
devproject/templates/emailconfirmation/confirm_email.html
dist/django-email-confirmation-0.1.3.tar.gz
django_email_confirmation.egg-info/PKG-INFO
django_email_confirmation.egg-info/SOURCES.txt
django_email_confirmation.egg-info/dependency_links.txt
django_email_confirmation.egg-info/not-zip-safe
django_email_confirmation.egg-info/top_level.txt
docs/index.txt
emailconfirmation/__init__.py
emailconfirmation/admin.py
emailconfirmation/models.py
emailconfirmation/signals.py
emailconfirmation/utils.py
emailconfirmation/views.py
emailconfirmation/templates/emailconfirmation/email_confirmation_message.txt
emailconfirmation/templates/emailconfirmation/email_confirmation_subject.txt