Metadata-Version: 1.0
Name: django-email-confirmation
Version: 0.1.4
Summary: Simple email confirmation for the Django web framework.
Home-page: http://code.google.com/p/django-email-confirmation/
Author: James Tauber
Author-email: jtauber@jtauber.com
License: UNKNOWN
Platform: UNKNOWN
Classifier: Development Status :: 3 - Alpha
Classifier: Environment :: Web Environment
Classifier: Intended Audience :: Developers
Classifier: License :: OSI Approved :: MIT License
Classifier: Operating System :: OS Independent
Classifier: Programming Language :: Python
Classifier: Framework :: Django
